{"data":{"wordpressPage":{"title":"WordPress Coding","content":"<p>When I first started building themes with WordPress, I spent a lot of time looking at other programmer’s code. I would find a snippet, pull it apart and learn from it. Rinse and repeat. I learnt a lot from this process, and occasionally still do. Other people will always be finding solutions to problems you have, or problems similar.</p>\n<p>&nbsp;</p>\n<p>I have decided to start posting specific snippets of code that I use time and time again for other people to get some use out of them, and learn as I did.</p>\n<p>&nbsp;</p>\n<p>All these snippets will be fully documented, so as to provide as much understanding as possible. I will also try to explain how they can be used, give ideas on how to adapt them, and link to other websites that I myself use.</p>\n","excerpt":"<p>When I first started building themes with WordPress, I spent a lot of time looking at other programmer’s code. I would find a snippet, pull it apart and learn from it. Rinse and repeat. I learnt a lot from this process, and occasionally still do. Other people will always be finding solutions to problems you [&hellip;]</p>\n","slug":"wordpress-coding","date":"2016-01-10T01:00:52.000Z","modified":"2016-01-10T01:00:52.000Z","yoast_meta":{"yoast_wpseo_title":"","yoast_wpseo_metadesc":"","yoast_wpseo_meta_robots_noindex":"","yoast_wpseo_meta_robots_nofollow":"","yoast_wpseo_canonical":"","yoast_wpseo_opengraph_title":"","yoast_wpseo_opengraph_description":"","yoast_wpseo_opengraph_image":"","yoast_wpseo_twitter_title":"","yoast_wpseo_twitter_description":"","yoast_wpseo_twitter_image":""}},"site":{"id":"Site","siteMetadata":{"title":"Website Design and Development Inspiration"}}},"pageContext":{"id":"c3ef137c-fa26-5b77-b178-b597af6632fa","slug":"wordpress-coding"}}